{"event": "2023", "members": {"3262187": {"completion_day_level": {"3": {"2": {"star_index": 597151, "get_star_ts": 1701600692}, "1": {"get_star_ts": 1701596714, "star_index": 583777}}, "1": {"1": {"star_index": 47019, "get_star_ts": 1701419670}, "2": {"star_index": 65178, "get_star_ts": 1701424279}}, "2": {"2": {"get_star_ts": 1701511116, "star_index": 339747}, "1": {"star_index": 337567, "get_star_ts": 1701510603}}, "4": {"2": {"get_star_ts": 1701684116, "star_index": 854708}, "1": {"star_index": 848002, "get_star_ts": 1701682571}}}, "global_score": 0, "stars": 8, "name": "Mohamed Aziz LASSOUED", "last_star_ts": 1701684116, "local_score": 310, "id": 3262187}, "970313": {"stars": 8, "global_score": 0, "completion_day_level": {"3": {"1": {"get_star_ts": 1701603452, "star_index": 606607}, "2": {"star_index": 619769, "get_star_ts": 1701607457}}, "1": {"1": {"star_index": 168559, "get_star_ts": 1701451922}, "2": {"get_star_ts": 1701455325, "star_index": 180887}}, "4": {"1": {"get_star_ts": 1701675584, "star_index": 818372}, "2": {"get_star_ts": 1701677125, "star_index": 824714}}, "2": {"2": {"get_star_ts": 1701533798, "star_index": 426446}, "1": {"star_index": 422540, "get_star_ts": 1701532718}}}, "id": 970313, "last_star_ts": 1701677125, "local_score": 247, "name": "Benoit"}, "979154": {"completion_day_level": {"2": {"2": {"get_star_ts": 1701679694, "star_index": 835626}, "1": {"star_index": 834725, "get_star_ts": 1701679480}}, "1": {"1": {"get_star_ts": 1701448750, "star_index": 156123}, "2": {"star_index": 161184, "get_star_ts": 1701450003}}, "3": {"1": {"star_index": 848888, "get_star_ts": 1701682778}}}, "stars": 5, "global_score": 0, "last_star_ts": 1701682778, "name": "Ga\u00eblle CHALOT", "local_score": 92, "id": 979154}, "3350016": {"stars": 8, "global_score": 0, "completion_day_level": {"3": {"2": {"star_index": 713115, "get_star_ts": 1701635831}, "1": {"get_star_ts": 1701626365, "star_index": 681919}}, "1": {"2": {"get_star_ts": 1701437343, "star_index": 110740}, "1": {"get_star_ts": 1701435007, "star_index": 102701}}, "2": {"1": {"get_star_ts": 1701554734, "star_index": 494053}, "2": {"star_index": 498752, "get_star_ts": 1701556454}}, "4": {"1": {"star_index": 834175, "get_star_ts": 1701679347}, "2": {"star_index": 856424, "get_star_ts": 1701684520}}}, "id": 3350016, "name": "Victor VOISIN", "last_star_ts": 1701684520, "local_score": 221}, "2335889": {"global_score": 0, "stars": 6, "completion_day_level": {"4": {"2": {"star_index": 948839, "get_star_ts": 1701709602}, "1": {"star_index": 916289, "get_star_ts": 1701700922}}, "2": {"1": {"get_star_ts": 1701684383, "star_index": 855873}, "2": {"star_index": 859460, "get_star_ts": 1701685294}}, "1": {"1": {"get_star_ts": 1701408296, "star_index": 9222}, "2": {"get_star_ts": 1701419175, "star_index": 45184}}}, "id": 2335889, "name": "Eolran", "last_star_ts": 1701709602, "local_score": 179}, "2670810": {"id": 2670810, "local_score": 151, "last_star_ts": 1701701082, "name": "Hugo De Grossi", "stars": 5, "global_score": 0, "completion_day_level": {"2": {"2": {"get_star_ts": 1701537585, "star_index": 440195}, "1": {"star_index": 438398, "get_star_ts": 1701537060}}, "1": {"2": {"star_index": 46054, "get_star_ts": 1701419417}, "1": {"get_star_ts": 1701417276, "star_index": 38673}}, "3": {"1": {"star_index": 916890, "get_star_ts": 1701701082}}}}, "2265940": {"id": 2265940, "name": "Olivier GR\u00c9GOIRE", "last_star_ts": 1701677816, "local_score": 240, "global_score": 0, "stars": 8, "completion_day_level": {"1": {"2": {"get_star_ts": 1701468305, "star_index": 224090}, "1": {"star_index": 223717, "get_star_ts": 1701468182}}, "4": {"2": {"star_index": 827522, "get_star_ts": 1701677816}, "1": {"star_index": 827103, "get_star_ts": 1701677710}}, "2": {"2": {"star_index": 368444, "get_star_ts": 1701518095}, "1": {"get_star_ts": 1701518005, "star_index": 368091}}, "3": {"2": {"star_index": 706454, "get_star_ts": 1701633843}, "1": {"star_index": 620647, "get_star_ts": 1701607725}}}}, "1591604": {"name": "Dylan KOEHL", "last_star_ts": 1701691994, "local_score": 240, "id": 1591604, "completion_day_level": {"4": {"2": {"star_index": 883572, "get_star_ts": 1701691994}, "1": {"get_star_ts": 1701688941, "star_index": 873218}}, "2": {"1": {"star_index": 331604, "get_star_ts": 1701509122}, "2": {"star_index": 334323, "get_star_ts": 1701509804}}, "1": {"2": {"get_star_ts": 1701452425, "star_index": 170381}, "1": {"get_star_ts": 1701440888, "star_index": 124225}}, "3": {"2": {"star_index": 649509, "get_star_ts": 1701616549}, "1": {"star_index": 645275, "get_star_ts": 1701615285}}}, "global_score": 0, "stars": 8}, "3276802": {"global_score": 0, "stars": 8, "completion_day_level": {"3": {"1": {"get_star_ts": 1701597650, "star_index": 586813}, "2": {"get_star_ts": 1701607040, "star_index": 618448}}, "1": {"2": {"star_index": 65811, "get_star_ts": 1701424431}, "1": {"star_index": 48340, "get_star_ts": 1701420033}}, "2": {"1": {"get_star_ts": 1701497062, "star_index": 291117}, "2": {"star_index": 292669, "get_star_ts": 1701497456}}, "4": {"1": {"star_index": 801178, "get_star_ts": 1701671012}, "2": {"star_index": 831001, "get_star_ts": 1701678618}}}, "id": 3276802, "last_star_ts": 1701678618, "local_score": 358, "name": "C\u00e9sar Vel\u00e1squez"}, "3641293": {"global_score": 0, "stars": 6, "completion_day_level": {"1": {"1": {"get_star_ts": 1701695501, "star_index": 895965}, "2": {"get_star_ts": 1701708305, "star_index": 944084}}, "4": {"1": {"star_index": 927355, "get_star_ts": 1701703869}, "2": {"get_star_ts": 1701705661, "star_index": 934125}}, "2": {"1": {"star_index": 912031, "get_star_ts": 1701699809}, "2": {"star_index": 913116, "get_star_ts": 1701700084}}}, "id": 3641293, "local_score": 89, "last_star_ts": 1701708305, "name": "Florian LIGNEUL"}, "729480": {"id": 729480, "last_star_ts": 1701683431, "local_score": 312, "name": "Yves DAUTREMAY", "global_score": 0, "stars": 8, "completion_day_level": {"3": {"2": {"get_star_ts": 1701613212, "star_index": 638539}, "1": {"get_star_ts": 1701611682, "star_index": 633625}}, "4": {"2": {"star_index": 851740, "get_star_ts": 1701683431}, "1": {"star_index": 847182, "get_star_ts": 1701682374}}, "2": {"2": {"star_index": 308438, "get_star_ts": 1701502317}, "1": {"star_index": 307090, "get_star_ts": 1701501854}}, "1": {"2": {"get_star_ts": 1701424827, "star_index": 67347}, "1": {"star_index": 49077, "get_star_ts": 1701420238}}}}, "2317893": {"global_score": 0, "stars": 8, "completion_day_level": {"3": {"1": {"get_star_ts": 1701588551, "star_index": 562454}, "2": {"get_star_ts": 1701588576, "star_index": 562533}}, "1": {"2": {"get_star_ts": 1701457043, "star_index": 186724}, "1": {"star_index": 186462, "get_star_ts": 1701456969}}, "4": {"1": {"get_star_ts": 1701671272, "star_index": 802151}, "2": {"star_index": 802189, "get_star_ts": 1701671283}}, "2": {"2": {"get_star_ts": 1701506506, "star_index": 322163}, "1": {"star_index": 322062, "get_star_ts": 1701506474}}}, "id": 2317893, "name": "St\u00e9phane Bierbaum", "last_star_ts": 1701671283, "local_score": 318}, "2524523": {"global_score": 0, "stars": 0, "completion_day_level": {}, "id": 2524523, "last_star_ts": 0, "name": "Antoine M\u00e9ausoone", "local_score": 0}, "3217630": {"id": 3217630, "last_star_ts": 1701644262, "local_score": 189, "name": "Baptiste PIRAULT", "stars": 6, "global_score": 0, "completion_day_level": {"1": {"1": {"get_star_ts": 1701439778, "star_index": 119909}, "2": {"get_star_ts": 1701442008, "star_index": 128778}}, "2": {"2": {"get_star_ts": 1701503661, "star_index": 312622}, "1": {"star_index": 311894, "get_star_ts": 1701503449}}, "3": {"2": {"star_index": 738975, "get_star_ts": 1701644262}, "1": {"star_index": 736011, "get_star_ts": 1701643074}}}}, "1313423": {"completion_day_level": {"1": {"1": {"get_star_ts": 1701408037, "star_index": 7708}, "2": {"get_star_ts": 1701414248, "star_index": 29351}}, "2": {"2": {"star_index": 304301, "get_star_ts": 1701500906}, "1": {"get_star_ts": 1701498249, "star_index": 295608}}, "4": {"2": {"get_star_ts": 1701676240, "star_index": 821028}, "1": {"get_star_ts": 1701669404, "star_index": 794533}}, "3": {"2": {"get_star_ts": 1701604575, "star_index": 610300}, "1": {"get_star_ts": 1701597191, "star_index": 585301}}}, "stars": 8, "global_score": 0, "last_star_ts": 1701676240, "name": "Frederick Vu", "local_score": 391, "id": 1313423}, "3284026": {"global_score": 0, "stars": 8, "completion_day_level": {"4": {"2": {"get_star_ts": 1701674305, "star_index": 813347}, "1": {"star_index": 809948, "get_star_ts": 1701673384}}, "2": {"1": {"get_star_ts": 1701507171, "star_index": 324441}, "2": {"get_star_ts": 1701508800, "star_index": 330403}}, "1": {"2": {"get_star_ts": 1701437892, "star_index": 112696}, "1": {"get_star_ts": 1701414430, "star_index": 29835}}, "3": {"1": {"star_index": 577924, "get_star_ts": 1701594727}, "2": {"get_star_ts": 1701599919, "star_index": 594445}}}, "id": 3284026, "last_star_ts": 1701674305, "local_score": 340, "name": "KurzF"}, "1101779": {"id": 1101779, "local_score": 92, "last_star_ts": 1701516732, "name": "Thierry Barnier", "stars": 3, "global_score": 0, "completion_day_level": {"1": {"1": {"get_star_ts": 1701423988, "star_index": 63975}}, "2": {"1": {"get_star_ts": 1701514156, "star_index": 352358}, "2": {"get_star_ts": 1701516732, "star_index": 363058}}}}, "2305200": {"completion_day_level": {"2": {"2": {"get_star_ts": 1701538003, "star_index": 441635}, "1": {"get_star_ts": 1701537220, "star_index": 438922}}, "4": {"1": {"get_star_ts": 1701711690, "star_index": 956202}, "2": {"star_index": 981617, "get_star_ts": 1701718946}}, "1": {"2": {"star_index": 35560, "get_star_ts": 1701416342}, "1": {"star_index": 27195, "get_star_ts": 1701413468}}, "3": {"1": {"star_index": 693462, "get_star_ts": 1701629968}, "2": {"get_star_ts": 1701645114, "star_index": 740922}}}, "global_score": 0, "stars": 8, "name": "Louis DELARUE", "last_star_ts": 1701718946, "local_score": 233, "id": 2305200}, "3257884": {"id": 3257884, "local_score": 255, "last_star_ts": 1701682479, "name": "Quentin DELATTRE", "global_score": 0, "stars": 8, "completion_day_level": {"1": {"1": {"get_star_ts": 1701417939, "star_index": 40844}, "2": {"star_index": 46475, "get_star_ts": 1701419531}}, "4": {"1": {"star_index": 833996, "get_star_ts": 1701679309}, "2": {"get_star_ts": 1701682479, "star_index": 847636}}, "2": {"2": {"star_index": 492178, "get_star_ts": 1701554082}, "1": {"star_index": 490328, "get_star_ts": 1701553431}}, "3": {"1": {"star_index": 697964, "get_star_ts": 1701631333}, "2": {"get_star_ts": 1701631583, "star_index": 698797}}}}, "3217604": {"stars": 0, "global_score": 0, "completion_day_level": {}, "id": 3217604, "last_star_ts": 0, "local_score": 0, "name": "Camille HENAULT"}, "835217": {"completion_day_level": {"1": {"1": {"star_index": 51436, "get_star_ts": 1701420839}}}, "stars": 1, "global_score": 0, "local_score": 34, "last_star_ts": 1701420839, "name": "ThomasGoetzmann", "id": 835217}, "659697": {"completion_day_level": {"2": {"2": {"get_star_ts": 1701527198, "star_index": 402408}, "1": {"get_star_ts": 1701526296, "star_index": 399047}}, "1": {"1": {"star_index": 212028, "get_star_ts": 1701464627}}}, "stars": 3, "global_score": 0, "name": "Raze Olivier", "last_star_ts": 1701527198, "local_score": 61, "id": 659697}, "971682": {"completion_day_level": {"3": {"2": {"get_star_ts": 1701630614, "star_index": 695546}, "1": {"get_star_ts": 1701619110, "star_index": 657731}}, "2": {"2": {"star_index": 294089, "get_star_ts": 1701497820}, "1": {"get_star_ts": 1701497238, "star_index": 291861}}, "4": {"2": {"get_star_ts": 1701709893, "star_index": 949787}, "1": {"star_index": 880696, "get_star_ts": 1701691165}}, "1": {"2": {"get_star_ts": 1701409492, "star_index": 14690}, "1": {"star_index": 13071, "get_star_ts": 1701409096}}}, "stars": 8, "global_score": 0, "name": "Erwan Le Tutour", "last_star_ts": 1701709893, "local_score": 327, "id": 971682}, "60864": {"stars": 8, "global_score": 0, "completion_day_level": {"4": {"1": {"get_star_ts": 1701666616, "star_index": 773106}, "2": {"star_index": 780328, "get_star_ts": 1701667282}}, "2": {"1": {"get_star_ts": 1701524053, "star_index": 390859}, "2": {"star_index": 393187, "get_star_ts": 1701524668}}, "1": {"1": {"get_star_ts": 1701410125, "star_index": 17108}, "2": {"get_star_ts": 1701451353, "star_index": 166413}}, "3": {"2": {"star_index": 550582, "get_star_ts": 1701584385}, "1": {"star_index": 549417, "get_star_ts": 1701584047}}}, "id": 60864, "name": "Fabian Pijcke", "last_star_ts": 1701667282, "local_score": 348}, "205230": {"id": 205230, "local_score": 291, "last_star_ts": 1701679328, "name": "geektortoise", "global_score": 0, "stars": 8, "completion_day_level": {"2": {"1": {"star_index": 448819, "get_star_ts": 1701540125}, "2": {"get_star_ts": 1701540921, "star_index": 451435}}, "4": {"2": {"get_star_ts": 1701679328, "star_index": 834086}, "1": {"get_star_ts": 1701677728, "star_index": 827184}}, "1": {"1": {"get_star_ts": 1701420467, "star_index": 50002}, "2": {"get_star_ts": 1701423613, "star_index": 62469}}, "3": {"2": {"star_index": 574508, "get_star_ts": 1701593440}, "1": {"get_star_ts": 1701592072, "star_index": 570949}}}}, "2369419": {"last_star_ts": 1701704507, "local_score": 285, "name": "Antoine Untereiner", "id": 2369419, "completion_day_level": {"4": {"2": {"star_index": 929767, "get_star_ts": 1701704507}, "1": {"star_index": 925003, "get_star_ts": 1701703250}}, "2": {"1": {"get_star_ts": 1701500634, "star_index": 303462}, "2": {"get_star_ts": 1701500862, "star_index": 304154}}, "1": {"1": {"get_star_ts": 1701415105, "star_index": 31811}, "2": {"star_index": 40360, "get_star_ts": 1701417785}}, "3": {"1": {"get_star_ts": 1701687742, "star_index": 869062}, "2": {"get_star_ts": 1701689215, "star_index": 874162}}}, "global_score": 0, "stars": 8}, "1678730": {"name": "Antoine Richard", "last_star_ts": 1701690964, "local_score": 256, "id": 1678730, "completion_day_level": {"3": {"1": {"star_index": 670803, "get_star_ts": 1701623034}, "2": {"star_index": 675228, "get_star_ts": 1701624348}}, "2": {"2": {"star_index": 383352, "get_star_ts": 1701522030}, "1": {"star_index": 381076, "get_star_ts": 1701521423}}, "4": {"2": {"get_star_ts": 1701690964, "star_index": 880024}, "1": {"star_index": 875654, "get_star_ts": 1701689669}}, "1": {"1": {"get_star_ts": 1701419977, "star_index": 48126}, "2": {"star_index": 65986, "get_star_ts": 1701424474}}}, "global_score": 0, "stars": 8}, "1501011": {"local_score": 126, "last_star_ts": 1701508739, "name": "Valentin LEFORT", "id": 1501011, "completion_day_level": {"1": {"1": {"star_index": 64297, "get_star_ts": 1701424064}, "2": {"star_index": 166189, "get_star_ts": 1701451291}}, "2": {"2": {"star_index": 330158, "get_star_ts": 1701508739}, "1": {"get_star_ts": 1701507667, "star_index": 326242}}}, "global_score": 0, "stars": 4}, "3295863": {"completion_day_level": {"1": {"1": {"get_star_ts": 1701437528, "star_index": 111401}, "2": {"star_index": 113144, "get_star_ts": 1701438020}}, "4": {"2": {"get_star_ts": 1701674462, "star_index": 814012}, "1": {"get_star_ts": 1701670352, "star_index": 798552}}, "2": {"1": {"star_index": 323576, "get_star_ts": 1701506917}, "2": {"star_index": 326943, "get_star_ts": 1701507864}}, "3": {"1": {"get_star_ts": 1701599753, "star_index": 593885}, "2": {"get_star_ts": 1701601407, "star_index": 599598}}}, "stars": 8, "global_score": 0, "last_star_ts": 1701674462, "local_score": 314, "name": "St\u00e9phane Kermabon", "id": 3295863}, "446961": {"completion_day_level": {"1": {"1": {"star_index": 41709, "get_star_ts": 1701418205}, "2": {"get_star_ts": 1701421064, "star_index": 52355}}}, "global_score": 0, "stars": 2, "last_star_ts": 1701421064, "local_score": 87, "name": "R\u00e9mi Duriez", "id": 446961}, "1035790": {"stars": 8, "global_score": 0, "completion_day_level": {"3": {"2": {"star_index": 550798, "get_star_ts": 1701584453}, "1": {"star_index": 548529, "get_star_ts": 1701583807}}, "4": {"1": {"get_star_ts": 1701669179, "star_index": 793382}, "2": {"star_index": 801237, "get_star_ts": 1701671027}}, "2": {"1": {"get_star_ts": 1701496992, "star_index": 290820}, "2": {"star_index": 292853, "get_star_ts": 1701497499}}, "1": {"1": {"star_index": 17460, "get_star_ts": 1701410229}, "2": {"star_index": 25241, "get_star_ts": 1701412794}}}, "id": 1035790, "last_star_ts": 1701671027, "name": "Hugo KAHLOUCH", "local_score": 427}, "3292611": {"name": "Abraham Giuliani", "last_star_ts": 1701678980, "local_score": 295, "id": 3292611, "completion_day_level": {"2": {"1": {"get_star_ts": 1701510171, "star_index": 335813}, "2": {"star_index": 346617, "get_star_ts": 1701512775}}, "4": {"1": {"get_star_ts": 1701678921, "star_index": 832358}, "2": {"get_star_ts": 1701678980, "star_index": 832565}}, "1": {"2": {"star_index": 85061, "get_star_ts": 1701429611}, "1": {"star_index": 77316, "get_star_ts": 1701427408}}, "3": {"2": {"get_star_ts": 1701602891, "star_index": 604696}, "1": {"get_star_ts": 1701602756, "star_index": 604163}}}, "stars": 8, "global_score": 0}, "988894": {"id": 988894, "last_star_ts": 1701669404, "local_score": 382, "name": "St\u00e9phane Lallemagne", "global_score": 0, "stars": 8, "completion_day_level": {"4": {"2": {"star_index": 794532, "get_star_ts": 1701669404}, "1": {"get_star_ts": 1701667967, "star_index": 786087}}, "2": {"2": {"get_star_ts": 1701495676, "star_index": 283945}, "1": {"star_index": 279643, "get_star_ts": 1701495064}}, "1": {"1": {"get_star_ts": 1701441289, "star_index": 125874}, "2": {"get_star_ts": 1701446540, "star_index": 147275}}, "3": {"2": {"star_index": 547032, "get_star_ts": 1701583402}, "1": {"get_star_ts": 1701583150, "star_index": 546086}}}}, "624919": {"id": 624919, "name": "Arnaud Le Bourblanc", "last_star_ts": 0, "local_score": 0, "stars": 0, "global_score": 0, "completion_day_level": {}}, "3589029": {"id": 3589029, "name": "Issam TELLISSI", "last_star_ts": 1701676845, "local_score": 200, "global_score": 0, "stars": 8, "completion_day_level": {"3": {"2": {"star_index": 692797, "get_star_ts": 1701629761}, "1": {"star_index": 689080, "get_star_ts": 1701628589}}, "4": {"2": {"get_star_ts": 1701676845, "star_index": 823575}, "1": {"get_star_ts": 1701675563, "star_index": 818283}}, "2": {"1": {"get_star_ts": 1701631131, "star_index": 697261}, "2": {"star_index": 699468, "get_star_ts": 1701631796}}, "1": {"1": {"get_star_ts": 1701615754, "star_index": 646802}, "2": {"star_index": 676054, "get_star_ts": 1701624588}}}}, "202047": {"global_score": 0, "stars": 0, "completion_day_level": {}, "id": 202047, "name": "gregorybarale", "last_star_ts": 0, "local_score": 0}, "1519674": {"completion_day_level": {"1": {"1": {"star_index": 137689, "get_star_ts": 1701444185}, "2": {"get_star_ts": 1701449009, "star_index": 157212}}, "2": {"2": {"get_star_ts": 1701501580, "star_index": 306326}, "1": {"star_index": 303901, "get_star_ts": 1701500778}}}, "global_score": 0, "stars": 4, "local_score": 139, "last_star_ts": 1701501580, "name": "Tanguy SIRONNEAU", "id": 1519674}, "1501049": {"id": 1501049, "name": "Yassine", "last_star_ts": 1701711169, "local_score": 31, "global_score": 0, "stars": 3, "completion_day_level": {"1": {"2": {"star_index": 812160, "get_star_ts": 1701673988}, "1": {"star_index": 661077, "get_star_ts": 1701620111}}, "2": {"1": {"get_star_ts": 1701711169, "star_index": 954358}}}}, "1503315": {"stars": 8, "global_score": 0, "completion_day_level": {"3": {"1": {"get_star_ts": 1701589777, "star_index": 565431}, "2": {"get_star_ts": 1701595425, "star_index": 579910}}, "2": {"1": {"star_index": 293900, "get_star_ts": 1701497772}, "2": {"get_star_ts": 1701499226, "star_index": 299008}}, "4": {"2": {"get_star_ts": 1701671359, "star_index": 802472}, "1": {"star_index": 787394, "get_star_ts": 1701668138}}, "1": {"2": {"star_index": 45539, "get_star_ts": 1701419277}, "1": {"get_star_ts": 1701413781, "star_index": 28080}}}, "id": 1503315, "name": "Mike SCHILLING", "last_star_ts": 1701671359, "local_score": 401}, "807776": {"id": 807776, "last_star_ts": 1701704813, "name": "Vincent Mariani", "local_score": 105, "global_score": 0, "stars": 3, "completion_day_level": {"4": {"1": {"star_index": 930919, "get_star_ts": 1701704813}}, "1": {"2": {"get_star_ts": 1701422905, "star_index": 59657}, "1": {"get_star_ts": 1701418544, "star_index": 42873}}}}, "903466": {"completion_day_level": {"2": {"2": {"star_index": 307355, "get_star_ts": 1701501944}, "1": {"star_index": 306276, "get_star_ts": 1701501566}}, "4": {"1": {"get_star_ts": 1701668217, "star_index": 787886}, "2": {"star_index": 797311, "get_star_ts": 1701670038}}, "1": {"1": {"star_index": 96809, "get_star_ts": 1701433225}, "2": {"star_index": 308944, "get_star_ts": 1701502498}}, "3": {"2": {"star_index": 567423, "get_star_ts": 1701590628}, "1": {"get_star_ts": 1701586704, "star_index": 557763}}}, "global_score": 0, "stars": 8, "last_star_ts": 1701670038, "local_score": 343, "name": "Hamadi JABLOUN", "id": 903466}, "3223731": {"last_star_ts": 1701706957, "name": "Brice KUCA", "local_score": 227, "id": 3223731, "completion_day_level": {"3": {"1": {"star_index": 665349, "get_star_ts": 1701621410}}, "1": {"2": {"star_index": 44311, "get_star_ts": 1701418939}, "1": {"star_index": 39363, "get_star_ts": 1701417479}}, "4": {"1": {"get_star_ts": 1701706957, "star_index": 939087}}, "2": {"2": {"star_index": 323491, "get_star_ts": 1701506889}, "1": {"star_index": 321876, "get_star_ts": 1701506422}}}, "global_score": 0, "stars": 6}, "3363997": {"global_score": 0, "stars": 8, "completion_day_level": {"3": {"2": {"get_star_ts": 1701687629, "star_index": 868648}, "1": {"get_star_ts": 1701685969, "star_index": 862153}}, "1": {"1": {"get_star_ts": 1701476382, "star_index": 244447}, "2": {"star_index": 359297, "get_star_ts": 1701515791}}, "2": {"2": {"get_star_ts": 1701507785, "star_index": 326651}, "1": {"star_index": 322228, "get_star_ts": 1701506520}}, "4": {"2": {"star_index": 883454, "get_star_ts": 1701691961}, "1": {"star_index": 870805, "get_star_ts": 1701688249}}}, "id": 3363997, "local_score": 207, "last_star_ts": 1701691961, "name": "Ali MAHFOUDHI"}, "3226299": {"global_score": 0, "stars": 8, "completion_day_level": {"3": {"2": {"get_star_ts": 1701627775, "star_index": 686484}, "1": {"get_star_ts": 1701623432, "star_index": 672132}}, "4": {"2": {"get_star_ts": 1701710721, "star_index": 952736}, "1": {"star_index": 939372, "get_star_ts": 1701707028}}, "2": {"2": {"get_star_ts": 1701525419, "star_index": 395974}, "1": {"get_star_ts": 1701524679, "star_index": 393234}}, "1": {"1": {"star_index": 51322, "get_star_ts": 1701420810}, "2": {"get_star_ts": 1701442141, "star_index": 129331}}}, "id": 3226299, "last_star_ts": 1701710721, "name": "Luiz Henriques", "local_score": 216}, "3217614": {"id": 3217614, "last_star_ts": 1701677587, "local_score": 380, "name": "uliseshdzc", "stars": 8, "global_score": 0, "completion_day_level": {"4": {"2": {"star_index": 826584, "get_star_ts": 1701677587}, "1": {"star_index": 810231, "get_star_ts": 1701673467}}, "2": {"1": {"get_star_ts": 1701499304, "star_index": 299253}, "2": {"star_index": 303400, "get_star_ts": 1701500616}}, "1": {"1": {"get_star_ts": 1701417266, "star_index": 38639}, "2": {"star_index": 53390, "get_star_ts": 1701421334}}, "3": {"1": {"star_index": 554722, "get_star_ts": 1701585648}, "2": {"get_star_ts": 1701587849, "star_index": 560735}}}}, "3198790": {"global_score": 0, "stars": 7, "completion_day_level": {"3": {"1": {"get_star_ts": 1701607648, "star_index": 620406}, "2": {"get_star_ts": 1701612069, "star_index": 634867}}, "1": {"1": {"star_index": 212660, "get_star_ts": 1701464824}, "2": {"get_star_ts": 1701474429, "star_index": 240652}}, "2": {"2": {"star_index": 351566, "get_star_ts": 1701513964}, "1": {"star_index": 346852, "get_star_ts": 1701512834}}, "4": {"1": {"star_index": 853376, "get_star_ts": 1701683802}}}, "id": 3198790, "local_score": 205, "last_star_ts": 1701683802, "name": "Julian Lefondeur"}, "3493726": {"id": 3493726, "local_score": 188, "last_star_ts": 1701692566, "name": "Lynda BENARAB", "stars": 8, "global_score": 0, "completion_day_level": {"3": {"1": {"star_index": 700052, "get_star_ts": 1701631951}, "2": {"star_index": 742703, "get_star_ts": 1701645905}}, "1": {"2": {"get_star_ts": 1701472678, "star_index": 236615}, "1": {"get_star_ts": 1701472272, "star_index": 235636}}, "2": {"1": {"star_index": 358533, "get_star_ts": 1701515608}, "2": {"get_star_ts": 1701547300, "star_index": 471625}}, "4": {"2": {"star_index": 885635, "get_star_ts": 1701692566}, "1": {"star_index": 866310, "get_star_ts": 1701687031}}}}, "3390396": {"id": 3390396, "last_star_ts": 1701435557, "name": "Maxime ZIMMER", "local_score": 25, "stars": 1, "global_score": 0, "completion_day_level": {"1": {"1": {"star_index": 104579, "get_star_ts": 1701435557}}}}, "2453222": {"stars": 8, "global_score": 0, "completion_day_level": {"4": {"1": {"star_index": 797354, "get_star_ts": 1701670048}, "2": {"get_star_ts": 1701671699, "star_index": 803763}}, "2": {"2": {"get_star_ts": 1701506940, "star_index": 323651}, "1": {"star_index": 322188, "get_star_ts": 1701506510}}, "1": {"2": {"star_index": 121892, "get_star_ts": 1701440307}, "1": {"star_index": 52283, "get_star_ts": 1701421046}}, "3": {"1": {"get_star_ts": 1701596928, "star_index": 584465}, "2": {"get_star_ts": 1701605640, "star_index": 613839}}}, "id": 2453222, "last_star_ts": 1701671699, "name": "Paul Robin", "local_score": 329}, "1007410": {"local_score": 452, "last_star_ts": 1701668949, "name": "David Junger", "id": 1007410, "completion_day_level": {"1": {"2": {"get_star_ts": 1701409702, "star_index": 15528}, "1": {"star_index": 0, "get_star_ts": 1701407134}}, "2": {"1": {"get_star_ts": 1701494189, "star_index": 271670}, "2": {"star_index": 274129, "get_star_ts": 1701494431}}, "4": {"2": {"star_index": 792216, "get_star_ts": 1701668949}, "1": {"star_index": 773815, "get_star_ts": 1701666678}}, "3": {"1": {"get_star_ts": 1701581700, "star_index": 539828}, "2": {"star_index": 549482, "get_star_ts": 1701584071}}}, "global_score": 0, "stars": 8}, "2900541": {"global_score": 0, "stars": 8, "completion_day_level": {"2": {"2": {"get_star_ts": 1701505306, "star_index": 318144}, "1": {"star_index": 315265, "get_star_ts": 1701504468}}, "4": {"1": {"star_index": 854380, "get_star_ts": 1701684038}, "2": {"star_index": 903440, "get_star_ts": 1701697548}}, "1": {"2": {"get_star_ts": 1701433954, "star_index": 99212}, "1": {"star_index": 62558, "get_star_ts": 1701423634}}, "3": {"1": {"get_star_ts": 1701605670, "star_index": 613950}, "2": {"star_index": 654887, "get_star_ts": 1701618234}}}, "id": 2900541, "last_star_ts": 1701697548, "name": "YouvaIBRAHIM", "local_score": 289}, "784619": {"name": "Lesage Yann", "last_star_ts": 1701672415, "local_score": 419, "id": 784619, "completion_day_level": {"1": {"2": {"star_index": 27141, "get_star_ts": 1701413446}, "1": {"star_index": 11221, "get_star_ts": 1701408686}}, "2": {"1": {"get_star_ts": 1701495480, "star_index": 282650}, "2": {"star_index": 288637, "get_star_ts": 1701496518}}, "4": {"2": {"star_index": 806373, "get_star_ts": 1701672415}, "1": {"star_index": 803317, "get_star_ts": 1701671585}}, "3": {"2": {"star_index": 556813, "get_star_ts": 1701586372}, "1": {"star_index": 554062, "get_star_ts": 1701585433}}}, "stars": 8, "global_score": 0}, "3226151": {"name": "Paul CHEVALIER", "last_star_ts": 1701707676, "local_score": 17, "id": 3226151, "completion_day_level": {"1": {"1": {"get_star_ts": 1701702510, "star_index": 922242}, "2": {"star_index": 941802, "get_star_ts": 1701707676}}}, "stars": 2, "global_score": 0}, "2317304": {"stars": 8, "global_score": 0, "completion_day_level": {"1": {"1": {"star_index": 111689, "get_star_ts": 1701437615}, "2": {"get_star_ts": 1701438687, "star_index": 115737}}, "2": {"2": {"star_index": 382051, "get_star_ts": 1701521682}, "1": {"get_star_ts": 1701521223, "star_index": 380351}}, "4": {"1": {"get_star_ts": 1701688497, "star_index": 871666}, "2": {"star_index": 873784, "get_star_ts": 1701689103}}, "3": {"2": {"get_star_ts": 1701687838, "star_index": 869409}, "1": {"star_index": 642676, "get_star_ts": 1701614477}}}, "id": 2317304, "name": "J\u00e9r\u00e9my HURE", "last_star_ts": 1701689103, "local_score": 228}, "3223714": {"stars": 8, "global_score": 0, "completion_day_level": {"3": {"2": {"get_star_ts": 1701647031, "star_index": 745050}, "1": {"get_star_ts": 1701612701, "star_index": 636897}}, "2": {"1": {"star_index": 382609, "get_star_ts": 1701521833}, "2": {"get_star_ts": 1701524145, "star_index": 391194}}, "4": {"2": {"star_index": 952949, "get_star_ts": 1701710781}, "1": {"star_index": 864282, "get_star_ts": 1701686518}}, "1": {"1": {"star_index": 68276, "get_star_ts": 1701425081}, "2": {"star_index": 95345, "get_star_ts": 1701432769}}}, "id": 3223714, "local_score": 231, "last_star_ts": 1701710781, "name": "Corentin KOZKA"}, "3637620": {"global_score": 0, "stars": 2, "completion_day_level": {"1": {"2": {"get_star_ts": 1701734701, "star_index": 1029060}, "1": {"get_star_ts": 1701732011, "star_index": 1024018}}}, "id": 3637620, "last_star_ts": 1701734701, "name": "spdy07", "local_score": 14}, "3217820": {"name": "Mehdi-17", "last_star_ts": 1701701779, "local_score": 195, "id": 3217820, "completion_day_level": {"4": {"2": {"get_star_ts": 1701701779, "star_index": 919538}, "1": {"star_index": 870891, "get_star_ts": 1701688269}}, "2": {"1": {"get_star_ts": 1701502414, "star_index": 308718}, "2": {"get_star_ts": 1701530798, "star_index": 415633}}, "1": {"1": {"get_star_ts": 1701473197, "star_index": 237890}, "2": {"get_star_ts": 1701535466, "star_index": 432622}}, "3": {"2": {"star_index": 753596, "get_star_ts": 1701652590}, "1": {"get_star_ts": 1701647938, "star_index": 746765}}}, "stars": 8, "global_score": 0}}, "owner_id": 624919}